[
  {
    "title_english": "Members",
    "title_chinese": "委員",
    "metadata": {
      "count": 133,
      "list_order_note": "Listed in the order of the number of strokes in their surnames"
    },
    "personnel": [
      {
        "name_pinyin": "Yu Shaoliang",
        "name_chinese": "于紹良",
        "dob_year": null,
        "dob_month": null,
        "assumed_office_date": null,
        "cross_reference_symbols": [],
        "gender": "male",
        "ethnicity": "Han",
        "rank": null,
        "rank_chinese": null,
        "other_notes": []
      },
      {
        "name_pinyin": "Wan Min",
        "name_chinese": "万敏",
        "dob_year": null,
        "dob_month": null,
        "assumed_office_date": null,
        "cross_reference_symbols": [],
        "gender": "male",
        "ethnicity": "Han",
        "rank": null,
        "rank_chinese": null,
        "other_notes": []
      },
      {
        "name_pinyin": "Xi Hua",
        "name_chinese": "習驊",
        "dob_year": null,
        "dob_month": null,
        "assumed_office_date": null,
        "cross_reference_symbols": [],
        "gender": "male",
        "ethnicity": "Han",
        "rank": null,
        "rank_chinese": null,
        "other_notes": []
      },
      {
        "name_pinyin": "Ma Xuedi",
        "name_chinese": "馬学蒂",
        "dob_year": null,
        "dob_month": null,
        "assumed_office_date": null,
        "cross_reference_symbols": [],
        "gender": "male",
        "ethnicity": "Han",
        "rank": null,
        "rank_chinese": null,
        "other_notes": []
      },
      {
        "name_pinyin": "Ma Senshu",
        "name_chinese": "馬森述",
        "dob_year": null,
        "dob_month": null,
        "assumed_office_date": null,
        "cross_reference_symbols": [],
        "gender": "male",
        "ethnicity": "Han",
        "rank": null,
        "rank_chinese": null,
        "other_notes": []
      },
      {
        "name_pinyin": "Wang Lin",
        "name_chinese": "王林",
        "dob_year": null,
        "dob_month": null,
        "assumed_office_date": null,
        "cross_reference_symbols": [],
        "gender": "male",
        "ethnicity": "Han",
        "rank": null,
        "rank_chinese": null,
        "other_notes": []
      },
      {
        "name_pinyin": "Wang Fu",
        "name_chinese": "王賦",
        "dob_year": null,
        "dob_month": null,
        "assumed_office_date": null,
        "cross_reference_symbols": [],
        "gender": "male",
        "ethnicity": "Han",
        "rank": null,
        "rank_chinese": null,
        "other_notes": []
      },
      {
        "name_pinyin": "Wang Weidong",
        "name_chinese": "王衛東",
        "dob_year": null,
        "dob_month": null,
        "assumed_office_date": null,
        "cross_reference_symbols": [],
        "gender": "male",
        "ethnicity": "Han",
        "rank": null,
        "rank_chinese": null,
        "other_notes": []
      },
      {
        "name_pinyin": "Wang Lishan",
        "name_chinese": "王立山",
        "dob_year": null,
        "dob_month": null,
        "assumed_office_date": null,
        "cross_reference_symbols": [],
        "gender": "male",
        "ethnicity": "Han",
        "rank": null,
        "rank_chinese": null,
        "other_notes": []
      },
      {
        "name_pinyin": "Wang Shuangquan",
        "name_chinese": "王双全",
        "dob_year": null,
        "dob_month": null,
        "assumed_office_date": null,
        "cross_reference_symbols": [],
        "gender": "male",
        "ethnicity": "Han",
        "rank": null,
        "rank_chinese": null,
        "other_notes": []
      },
      {
        "name_pinyin": "Wang Xingning",
        "name_chinese": "王興寧",
        "dob_year": null,
        "dob_month": null,
        "assumed_office_date": null,
        "cross_reference_symbols": [],
        "gender": "male",
        "ethnicity": "Han",
        "rank": null,
        "rank_chinese": null,
        "other_notes": []
      },
      {
        "name_pinyin": "Wang Lujin",
        "name_chinese": "王陸進",
        "dob_year": null,
        "dob_month": null,
        "assumed_office_date": null,
        "cross_reference_symbols": [],
        "gender": "male",
        "ethnicity": "Han",
        "rank": null,
        "rank_chinese": null,
        "other_notes": []
      },
      {
        "name_pinyin": "Wang Jianxin",
        "name_chinese": "王建新",
        "dob_year": null,
        "dob_month": null,
        "assumed_office_date": null,
        "cross_reference_symbols": [],
        "gender": "male",
        "ethnicity": "Han",
        "rank": null,
        "rank_chinese": null,
        "other_notes": []
      },
      {
        "name_pinyin": "Wang Yongjun",
        "name_chinese": "王擁軍",
        "dob_year": null,
        "dob_month": null,
        "assumed_office_date": null,
        "cross_reference_symbols": [],
        "gender": "male",
        "ethnicity": "Han",
        "rank": null,
        "rank_chinese": null,
        "other_notes": []
      },
      {
        "name_pinyin": "Wang Chengwen",
        "name_chinese": "王承文",
        "dob_year": null,
        "dob_month": null,
        "assumed_office_date": null,
        "cross_reference_symbols": [],
        "gender": "male",
        "ethnicity": "Han",
        "rank": null,
        "rank_chinese": null,
        "other_notes": []
      },
      {
        "name_pinyin": "Wang Aiwen",
        "name_chinese": "王愛文",
        "dob_year": null,
        "dob_month": null,
        "assumed_office_date": null,
        "cross_reference_symbols": [],
        "gender": "male",
        "ethnicity": "Han",
        "rank": null,
        "rank_chinese": null,
        "other_notes": []
      },
      {
        "name_pinyin": "Wang Hongjin",
        "name_chinese": "王鴻津",
        "dob_year": null,
        "dob_month": null,
        "assumed_office_date": null,
        "cross_reference_symbols": [],
        "gender": "male",
        "ethnicity": "Han",
        "rank": null,
        "rank_chinese": null,
        "other_notes": []
      },
      {
        "name_pinyin": "Wang Xinzhe",
        "name_chinese": "王新哲",
        "dob_year": null,
        "dob_month": null,
        "assumed_office_date": null,
        "cross_reference_symbols": [],
        "gender": "male",
        "ethnicity": "Han",
        "rank": null,
        "rank_chinese": null,
        "other_notes": []
      },
      {
        "name_pinyin": "Wang Xiaoping (f)",
        "name_chinese": "王曉萍",
        "dob_year": null,
        "dob_month": null,
        "assumed_office_date": null,
        "cross_reference_symbols": [],
        "gender": "female",
        "ethnicity": "Han",
        "rank": null,
        "rank_chinese": null,
        "other_notes": []
      },
      {
        "name_pinyin": "Wang Changsong",
        "name_chinese": "王常松",
        "dob_year": null,
        "dob_month": null,
        "assumed_office_date": null,
        "cross_reference_symbols": [],
        "gender": "male",
        "ethnicity": "Han",
        "rank": null,
        "rank_chinese": null,
        "other_notes": []
      },
      {
        "name_pinyin": "Wang Yuwen",
        "name_chinese": "王裕文",
        "dob_year": null,
        "dob_month": null,
        "assumed_office_date": null,
        "cross_reference_symbols": [],
        "gender": "male",
        "ethnicity": "Han",
        "rank": null,
        "rank_chinese": null,
        "other_notes": []
      },
      {
        "name_pinyin": "Wang Huimin",
        "name_chinese": "王慧敏",
        "dob_year": null,
        "dob_month": null,
        "assumed_office_date": null,
        "cross_reference_symbols": [],
        "gender": "male",
        "ethnicity": "Han",
        "rank": null,
        "rank_chinese": null,
        "other_notes": []
      },
      {
        "name_pinyin": "Ai Juntao",
        "name_chinese": "艾俊濤",
        "dob_year": null,
        "dob_month": null,
        "assumed_office_date": null,
        "cross_reference_symbols": [],
        "gender": "male",
        "ethnicity": "Han",
        "rank": null,
        "rank_chinese": null,
        "other_notes": []
      },
      {
        "name_pinyin": "Ye Min",
        "name_chinese": "葉民",
        "dob_year": null,
        "dob_month": null,
        "assumed_office_date": null,
        "cross_reference_symbols": [],
        "gender": "male",
        "ethnicity": "Han",
        "rank": null,
        "rank_chinese": null,
        "other_notes": []
      },
      {
        "name_pinyin": "Tian Xiangli",
        "name_chinese": "田湘利",
        "dob_year": null,
        "dob_month": null,
        "assumed_office_date": null,
        "cross_reference_symbols": [],
        "gender": "male",
        "ethnicity": "Han",
        "rank": null,
        "rank_chinese": null,
        "other_notes": []
      },
      {
        "name_pinyin": "Feng Zhili",
        "name_chinese": "馮志礼",
        "dob_year": null,
        "dob_month": null,
        "assumed_office_date": null,
        "cross_reference_symbols": [],
        "gender": "male",
        "ethnicity": "Han",
        "rank": null,
        "rank_chinese": null,
        "other_notes": []
      },
      {
        "name_pinyin": "Bian Xuewen",
        "name_chinese": "辺学文",
        "dob_year": null,
        "dob_month": null,
        "assumed_office_date": null,
        "cross_reference_symbols": [],
        "gender": "male",
        "ethnicity": "Han",
        "rank": null,
        "rank_chinese": null,
        "other_notes": []
      },
      {
        "name_pinyin": "Qu Xiaoli (f)",
        "name_chinese": "曲孝麗",
        "dob_year": null,
        "dob_month": null,
        "assumed_office_date": null,
        "cross_reference_symbols": [],
        "gender": "female",
        "ethnicity": "Han",
        "rank": null,
        "rank_chinese": null,
        "other_notes": []
      },
      {
        "name_pinyin": "Qu Jishan",
        "name_chinese": "曲吉山",
        "dob_year": null,
        "dob_month": null,
        "assumed_office_date": null,
        "cross_reference_symbols": [],
        "gender": "male",
        "ethnicity": "Han",
        "rank": null,
        "rank_chinese": null,
        "other_notes": []
      },
      {
        "name_pinyin": "Zhu Guobiao",
        "name_chinese": "朱国標",
        "dob_year": null,
        "dob_month": null,
        "assumed_office_date": null,
        "cross_reference_symbols": [],
        "gender": "male",
        "ethnicity": "Han",
        "rank": null,
        "rank_chinese": null,
        "other_notes": []
      },
      {
        "name_pinyin": "Lu Yansong",
        "name_chinese": "呂岩松",
        "dob_year": null,
        "dob_month": null,
        "assumed_office_date": null,
        "cross_reference_symbols": [],
        "gender": "male",
        "ethnicity": "Han",
        "rank": null,
        "rank_chinese": null,
        "other_notes": []
      },
      {
        "name_pinyin": "Ren Hongbin",
        "name_chinese": "任洪斌",
        "dob_year": null,
        "dob_month": null,
        "assumed_office_date": null,
        "cross_reference_symbols": [],
        "gender": "male",
        "ethnicity": "Han",
        "rank": null,
        "rank_chinese": null,
        "other_notes": []
      },
      {
        "name_pinyin": "Ren Airong (f)",
        "name_chinese": "任愛栄",
        "dob_year": null,
        "dob_month": null,
        "assumed_office_date": null,
        "cross_reference_symbols": [],
        "gender": "female",
        "ethnicity": "Han",
        "rank": null,
        "rank_chinese": null,
        "other_notes": []
      },
      {
        "name_pinyin": "Ren Hongbin (Tujia)",
        "name_chinese": "任鴻斌",
        "dob_year": null,
        "dob_month": null,
        "assumed_office_date": null,
        "cross_reference_symbols": [],
        "gender": "male",
        "ethnicity": "Tujia",
        "rank": null,
        "rank_chinese": null,
        "other_notes": []
      },
      {
        "name_pinyin": "Liu Jun",
        "name_chinese": "劉軍",
        "dob_year": null,
        "dob_month": null,
        "assumed_office_date": null,
        "cross_reference_symbols": [],
        "gender": "male",
        "ethnicity": "Han",
        "rank": null,
        "rank_chinese": null,
        "other_notes": []
      },
      {
        "name_pinyin": "Liu Zhao",
        "name_chinese": "劉炤",
        "dob_year": null,
        "dob_month": null,
        "assumed_office_date": null,
        "cross_reference_symbols": [],
        "gender": "male",
        "ethnicity": "Han",
        "rank": null,
        "rank_chinese": null,
        "other_notes": []
      },
      {
        "name_pinyin": "Liu Shuang",
        "name_chinese": "劉爽",
        "dob_year": null,
        "dob_month": null,
        "assumed_office_date": null,
        "cross_reference_symbols": [],
        "gender": "male",
        "ethnicity": "Han",
        "rank": null,
        "rank_chinese": null,
        "other_notes": []
      },
      {
        "name_pinyin": "Liu Xunyan",
        "name_chinese": "劉訓言",
        "dob_year": null,
        "dob_month": null,
        "assumed_office_date": null,
        "cross_reference_symbols": [],
        "gender": "male",
        "ethnicity": "Han",
        "rank": null,
        "rank_chinese": null,
        "other_notes": []
      },
      {
        "name_pinyin": "Liu Qifan",
        "name_chinese": "劉奇凡",
        "dob_year": null,
        "dob_month": null,
        "assumed_office_date": null,
        "cross_reference_symbols": [],
        "gender": "male",
        "ethnicity": "Han",
        "rank": null,
        "rank_chinese": null,
        "other_notes": []
      },
      {
        "name_pinyin": "Liu Junchuan",
        "name_chinese": "劉軍川",
        "dob_year": null,
        "dob_month": null,
        "assumed_office_date": null,
        "cross_reference_symbols": [],
        "gender": "male",
        "ethnicity": "Han",
        "rank": null,
        "rank_chinese": null,
        "other_notes": []
      },
      {
        "name_pinyin": "Liu Changlin",
        "name_chinese": "劉昌林",
        "dob_year": null,
        "dob_month": null,
        "assumed_office_date": null,
        "cross_reference_symbols": [],
        "gender": "male",
        "ethnicity": "Han",
        "rank": null,
        "rank_chinese": null,
        "other_notes": []
      },
      {
        "name_pinyin": "Liu Jinguo",
        "name_chinese": "劉金国",
        "dob_year": null,
        "dob_month": null,
        "assumed_office_date": null,
        "cross_reference_symbols": [
          "◎"
        ],
        "gender": "male",
        "ethnicity": "Han",
        "rank": null,
        "rank_chinese": null,
        "other_notes": []
      },
      {
        "name_pinyin": "Liu Xuexin",
        "name_chinese": "劉学新",
        "dob_year": null,
        "dob_month": null,
        "assumed_office_date": null,
        "cross_reference_symbols": [],
        "gender": "male",
        "ethnicity": "Han",
        "rank": null,
        "rank_chinese": null,
        "other_notes": []
      },
      {
        "name_pinyin": "Liu Meipin",
        "name_chinese": "劉美頻",
        "dob_year": null,
        "dob_month": null,
        "assumed_office_date": null,
        "cross_reference_symbols": [],
        "gender": "male",
        "ethnicity": "Han",
        "rank": null,
        "rank_chinese": null,
        "other_notes": []
      },
      {
        "name_pinyin": "Liu Haiquan",
        "name_chinese": "劉海泉",
        "dob_year": null,
        "dob_month": null,
        "assumed_office_date": null,
        "cross_reference_symbols": [],
        "gender": "male",
        "ethnicity": "Han",
        "rank": null,
        "rank_chinese": null,
        "other_notes": []
      },
      {
        "name_pinyin": "Xu Luode",
        "name_chinese": "許羅徳",
        "dob_year": null,
        "dob_month": null,
        "assumed_office_date": null,
        "cross_reference_symbols": [],
        "gender": "male",
        "ethnicity": "Han",
        "rank": null,
        "rank_chinese": null,
        "other_notes": []
      },
      {
        "name_pinyin": "Xu Xianping",
        "name_chinese": "許憲平",
        "dob_year": null,
        "dob_month": null,
        "assumed_office_date": null,
        "cross_reference_symbols": [],
        "gender": "male",
        "ethnicity": "Han",
        "rank": null,
        "rank_chinese": null,
        "other_notes": []
      },
      {
        "name_pinyin": "Sun Bin",
        "name_chinese": "孫斌",
        "dob_year": null,
        "dob_month": null,
        "assumed_office_date": null,
        "cross_reference_symbols": [],
        "gender": "male",
        "ethnicity": "Han",
        "rank": null,
        "rank_chinese": null,
        "other_notes": []
      },
      {
        "name_pinyin": "Sun Yegang",
        "name_chinese": "孫也剛",
        "dob_year": null,
        "dob_month": null,
        "assumed_office_date": null,
        "cross_reference_symbols": [],
        "gender": "male",
        "ethnicity": "Han",
        "rank": null,
        "rank_chinese": null,
        "other_notes": []
      },
      {
        "name_pinyin": "Sun Huaixin",
        "name_chinese": "孫懷新",
        "dob_year": null,
        "dob_month": null,
        "assumed_office_date": null,
        "cross_reference_symbols": [],
        "gender": "male",
        "ethnicity": "Han",
        "rank": null,
        "rank_chinese": null,
        "other_notes": []
      },
      {
        "name_pinyin": "Sun Xinyang",
        "name_chinese": "孫新陽",
        "dob_year": null,
        "dob_month": null,
        "assumed_office_date": null,
        "cross_reference_symbols": [],
        "gender": "male",
        "ethnicity": "Han",
        "rank": null,
        "rank_chinese": null,
        "other_notes": []
      },
      {
        "name_pinyin": "Li Jun",
        "name_chinese": "李軍",
        "dob_year": null,
        "dob_month": null,
        "assumed_office_date": null,
        "cross_reference_symbols": [],
        "gender": "male",
        "ethnicity": "Han",
        "rank": null,
        "rank_chinese": null,
        "other_notes": []
      },
      {
        "name_pinyin": "Li Xi",
        "name_chinese": "李希",
        "dob_year": null,
        "dob_month": null,
        "assumed_office_date": null,
        "cross_reference_symbols": [
          "☆"
        ],
        "gender": "male",
        "ethnicity": "Han",
        "rank": null,
        "rank_chinese": null,
        "other_notes": []
      },
      {
        "name_pinyin": "Li Yuanping",
        "name_chinese": "李元平",
        "dob_year": null,
        "dob_month": null,
        "assumed_office_date": null,
        "cross_reference_symbols": [],
        "gender": "male",
        "ethnicity": "Han",
        "rank": null,
        "rank_chinese": null,
        "other_notes": []
      },
      {
        "name_pinyin": "Li Yangzhe",
        "name_chinese": "李仰哲",
        "dob_year": null,
        "dob_month": null,
        "assumed_office_date": null,
        "cross_reference_symbols": [],
        "gender": "male",
        "ethnicity": "Han",
        "rank": null,
        "rank_chinese": null,
        "other_notes": []
      },
      {
        "name_pinyin": "Li Zhaozong",
        "name_chinese": "李兆宗",
        "dob_year": null,
        "dob_month": null,
        "assumed_office_date": null,
        "cross_reference_symbols": [],
        "gender": "male",
        "ethnicity": "Han",
        "rank": null,
        "rank_chinese": null,
        "other_notes": []
      },
      {
        "name_pinyin": "Li Xinran (Manchu)",
        "name_chinese": "李欣然",
        "dob_year": null,
        "dob_month": null,
        "assumed_office_date": null,
        "cross_reference_symbols": [],
        "gender": "male",
        "ethnicity": "Manchu",
        "rank": null,
        "rank_chinese": null,
        "other_notes": []
      },
      {
        "name_pinyin": "Li Yingchun",
        "name_chinese": "李迎春",
        "dob_year": null,
        "dob_month": null,
        "assumed_office_date": null,
        "cross_reference_symbols": [],
        "gender": "male",
        "ethnicity": "Han",
        "rank": null,
        "rank_chinese": null,
        "other_notes": []
      },
      {
        "name_pinyin": "Li Jinying (f/Hui)",
        "name_chinese": "李金英",
        "dob_year": null,
        "dob_month": null,
        "assumed_office_date": null,
        "cross_reference_symbols": [],
        "gender": "female",
        "ethnicity": "Hui",
        "rank": null,
        "rank_chinese": null,
        "other_notes": []
      },
      {
        "name_pinyin": "Li Jianming",
        "name_chinese": "李建明",
        "dob_year": null,
        "dob_month": null,
        "assumed_office_date": null,
        "cross_reference_symbols": [],
        "gender": "male",
        "ethnicity": "Han",
        "rank": null,
        "rank_chinese": null,
        "other_notes": []
      },
      {
        "name_pinyin": "Yang Guozhong",
        "name_chinese": "楊国中",
        "dob_year": null,
        "dob_month": null,
        "assumed_office_date": null,
        "cross_reference_symbols": [],
        "gender": "male",
        "ethnicity": "Han",
        "rank": null,
        "rank_chinese": null,
        "other_notes": []
      },
      {
        "name_pinyin": "Yang Xiaoxiang",
        "name_chinese": "楊笑祥",
        "dob_year": null,
        "dob_month": null,
        "assumed_office_date": null,
        "cross_reference_symbols": [],
        "gender": "male",
        "ethnicity": "Han",
        "rank": null,
        "rank_chinese": null,
        "other_notes": []
      },
      {
        "name_pinyin": "Yang Yizheng (f)",
        "name_chinese": "楊逸鈴",
        "dob_year": null,
        "dob_month": null,
        "assumed_office_date": null,
        "cross_reference_symbols": [],
        "gender": "female",
        "ethnicity": "Han",
        "rank": null,
        "rank_chinese": null,
        "other_notes": []
      },
      {
        "name_pinyin": "Xiao Pei",
        "name_chinese": "肖培",
        "dob_year": null,
        "dob_month": null,
        "assumed_office_date": null,
        "cross_reference_symbols": [
          "◎"
        ],
        "gender": "male",
        "ethnicity": "Han",
        "rank": null,
        "rank_chinese": null,
        "other_notes": []
      },
      {
        "name_pinyin": "Wu Qinghai",
        "name_chinese": "吳清海",
        "dob_year": null,
        "dob_month": null,
        "assumed_office_date": null,
        "cross_reference_symbols": [],
        "gender": "male",
        "ethnicity": "Han",
        "rank": null,
        "rank_chinese": null,
        "other_notes": []
      },
      {
        "name_pinyin": "Wu Daohuai",
        "name_chinese": "吳道槐",
        "dob_year": null,
        "dob_month": null,
        "assumed_office_date": null,
        "cross_reference_symbols": [],
        "gender": "male",
        "ethnicity": "Han",
        "rank": null,
        "rank_chinese": null,
        "other_notes": []
      },
      {
        "name_pinyin": "Yu Yonghong",
        "name_chinese": "余永洪",
        "dob_year": null,
        "dob_month": null,
        "assumed_office_date": null,
        "cross_reference_symbols": [],
        "gender": "male",
        "ethnicity": "Han",
        "rank": null,
        "rank_chinese": null,
        "other_notes": []
      },
      {
        "name_pinyin": "Zou Tianjing",
        "name_chinese": "鄒天敬",
        "dob_year": null,
        "dob_month": null,
        "assumed_office_date": null,
        "cross_reference_symbols": [],
        "gender": "male",
        "ethnicity": "Han",
        "rank": null,
        "rank_chinese": null,
        "other_notes": []
      },
      {
        "name_pinyin": "Leng Shaojie",
        "name_chinese": "冷少杰",
        "dob_year": null,
        "dob_month": null,
        "assumed_office_date": null,
        "cross_reference_symbols": [],
        "gender": "male",
        "ethnicity": "Han",
        "rank": null,
        "rank_chinese": null,
        "other_notes": []
      },
      {
        "name_pinyin": "Wang Yang",
        "name_chinese": "汪洋",
        "dob_year": null,
        "dob_month": null,
        "assumed_office_date": null,
        "cross_reference_symbols": [],
        "gender": "male",
        "ethnicity": "Han",
        "rank": null,
        "rank_chinese": null,
        "other_notes": []
      },
      {
        "name_pinyin": "Wang Hongyan",
        "name_chinese": "汪鴻雁",
        "dob_year": null,
        "dob_month": null,
        "assumed_office_date": null,
        "cross_reference_symbols": [],
        "gender": "male",
        "ethnicity": "Han",
        "rank": null,
        "rank_chinese": null,
        "other_notes": []
      },
      {
        "name_pinyin": "Shen Xiaohui",
        "name_chinese": "沈曉暉",
        "dob_year": null,
        "dob_month": null,
        "assumed_office_date": null,
        "cross_reference_symbols": [],
        "gender": "male",
        "ethnicity": "Han",
        "rank": null,
        "rank_chinese": null,
        "other_notes": []
      },
      {
        "name_pinyin": "Song Yijia (f)",
        "name_chinese": "宋依佳",
        "dob_year": null,
        "dob_month": null,
        "assumed_office_date": null,
        "cross_reference_symbols": [],
        "gender": "female",
        "ethnicity": "Han",
        "rank": null,
        "rank_chinese": null,
        "other_notes": []
      },
      {
        "name_pinyin": "Song Hansong",
        "name_chinese": "宋寒松",
        "dob_year": null,
        "dob_month": null,
        "assumed_office_date": null,
        "cross_reference_symbols": [],
        "gender": "male",
        "ethnicity": "Han",
        "rank": null,
        "rank_chinese": null,
        "other_notes": []
      },
      {
        "name_pinyin": "Song Demin",
        "name_chinese": "宋徳民",
        "dob_year": null,
        "dob_month": null,
        "assumed_office_date": null,
        "cross_reference_symbols": [],
        "gender": "male",
        "ethnicity": "Han",
        "rank": null,
        "rank_chinese": null,
        "other_notes": []
      },
      {
        "name_pinyin": "Song Fulong",
        "name_chinese": "宋福龍",
        "dob_year": null,
        "dob_month": null,
        "assumed_office_date": null,
        "cross_reference_symbols": [],
        "gender": "male",
        "ethnicity": "Han",
        "rank": null,
        "rank_chinese": null,
        "other_notes": []
      },
      {
        "name_pinyin": "Chi Yaoyun",
        "name_chinese": "遅耀雲",
        "dob_year": null,
        "dob_month": null,
        "assumed_office_date": null,
        "cross_reference_symbols": [],
        "gender": "male",
        "ethnicity": "Han",
        "rank": null,
        "rank_chinese": null,
        "other_notes": []
      },
      {
        "name_pinyin": "Zhang Jun (BIT)",
        "name_chinese": "張軍",
        "dob_year": null,
        "dob_month": null,
        "assumed_office_date": null,
        "cross_reference_symbols": [],
        "gender": "male",
        "ethnicity": "Han",
        "rank": null,
        "rank_chinese": null,
        "other_notes": [
          "BIT",
          "北京理工大"
        ]
      },
      {
        "name_pinyin": "Zhang Zhong",
        "name_chinese": "張忠",
        "dob_year": null,
        "dob_month": null,
        "assumed_office_date": null,
        "cross_reference_symbols": [],
        "gender": "male",
        "ethnicity": "Han",
        "rank": null,
        "rank_chinese": null,
        "other_notes": []
      },
      {
        "name_pinyin": "Zhang Min (f)",
        "name_chinese": "張敏",
        "dob_year": null,
        "dob_month": null,
        "assumed_office_date": null,
        "cross_reference_symbols": [],
        "gender": "female",
        "ethnicity": "Han",
        "rank": null,
        "rank_chinese": null,
        "other_notes": []
      },
      {
        "name_pinyin": "Zhang Ji",
        "name_chinese": "張　",
        "dob_year": null,
        "dob_month": null,
        "assumed_office_date": null,
        "cross_reference_symbols": [],
        "gender": "male",
        "ethnicity": "Han",
        "rank": null,
        "rank_chinese": null,
        "other_notes": []
      },
      {
        "name_pinyin": "Zhang Wei",
        "name_chinese": "張巍",
        "dob_year": null,
        "dob_month": null,
        "assumed_office_date": null,
        "cross_reference_symbols": [],
        "gender": "male",
        "ethnicity": "Han",
        "rank": null,
        "rank_chinese": null,
        "other_notes": []
      },
      {
        "name_pinyin": "Zhang Yiquan",
        "name_chinese": "張義全",
        "dob_year": null,
        "dob_month": null,
        "assumed_office_date": null,
        "cross_reference_symbols": [],
        "gender": "male",
        "ethnicity": "Han",
        "rank": null,
        "rank_chinese": null,
        "other_notes": []
      },
      {
        "name_pinyin": "Zhang Tianbao",
        "name_chinese": "張天宝",
        "dob_year": null,
        "dob_month": null,
        "assumed_office_date": null,
        "cross_reference_symbols": [],
        "gender": "male",
        "ethnicity": "Han",
        "rank": null,
        "rank_chinese": null,
        "other_notes": []
      },
      {
        "name_pinyin": "Zhang Shengmin (Gen)",
        "name_chinese": "張昇民",
        "dob_year": null,
        "dob_month": null,
        "assumed_office_date": null,
        "cross_reference_symbols": [
          "◎"
        ],
        "gender": "male",
        "ethnicity": "Han",
        "rank": "General",
        "rank_chinese": "上将",
        "other_notes": []
      },
      {
        "name_pinyin": "Zhang Jiwen",
        "name_chinese": "張際文",
        "dob_year": null,
        "dob_month": null,
        "assumed_office_date": null,
        "cross_reference_symbols": [],
        "gender": "male",
        "ethnicity": "Han",
        "rank": null,
        "rank_chinese": null,
        "other_notes": []
      },
      {
        "name_pinyin": "Zhang Rongshun",
        "name_chinese": "張榮順",
        "dob_year": null,
        "dob_month": null,
        "assumed_office_date": null,
        "cross_reference_symbols": [],
        "gender": "male",
        "ethnicity": "Han",
        "rank": null,
        "rank_chinese": null,
        "other_notes": []
      },
      {
        "name_pinyin": "Zhang Aihua",
        "name_chinese": "張愛華",
        "dob_year": null,
        "dob_month": null,
        "assumed_office_date": null,
        "cross_reference_symbols": [],
        "gender": "male",
        "ethnicity": "Han",
        "rank": null,
        "rank_chinese": null,
        "other_notes": []
      },
      {
        "name_pinyin": "Zhang Fuhai",
        "name_chinese": "張福海",
        "dob_year": null,
        "dob_month": null,
        "assumed_office_date": null,
        "cross_reference_symbols": [],
        "gender": "male",
        "ethnicity": "Han",
        "rank": null,
        "rank_chinese": null,
        "other_notes": []
      },
      {
        "name_pinyin": "Zhang Shuguang",
        "name_chinese": "張曙光",
        "dob_year": null,
        "dob_month": null,
        "assumed_office_date": null,
        "cross_reference_symbols": [],
        "gender": "male",
        "ethnicity": "Han",
        "rank": null,
        "rank_chinese": null,
        "other_notes": []
      },
      {
        "name_pinyin": "Lu Junhua",
        "name_chinese": "陸俊華",
        "dob_year": null,
        "dob_month": null,
        "assumed_office_date": null,
        "cross_reference_symbols": [],
        "gender": "male",
        "ethnicity": "Han",
        "rank": null,
        "rank_chinese": null,
        "other_notes": []
      },
      {
        "name_pinyin": "Chen Jian",
        "name_chinese": "陳健",
        "dob_year": null,
        "dob_month": null,
        "assumed_office_date": null,
        "cross_reference_symbols": [],
        "gender": "male",
        "ethnicity": "Han",
        "rank": null,
        "rank_chinese": null,
        "other_notes": []
      },
      {
        "name_pinyin": "Chen Guomeng",
        "name_chinese": "陳国猛",
        "dob_year": null,
        "dob_month": null,
        "assumed_office_date": null,
        "cross_reference_symbols": [],
        "gender": "male",
        "ethnicity": "Han",
        "rank": null,
        "rank_chinese": null,
        "other_notes": []
      },
      {
        "name_pinyin": "Chen Guoqiang (Lt. Gen)",
        "name_chinese": "陳国強",
        "dob_year": null,
        "dob_month": null,
        "assumed_office_date": null,
        "cross_reference_symbols": [],
        "gender": "male",
        "ethnicity": "Han",
        "rank": "Lieutenant General",
        "rank_chinese": "中将",
        "other_notes": []
      },
      {
        "name_pinyin": "Chen Jianfei",
        "name_chinese": "陳劍飛",
        "dob_year": null,
        "dob_month": null,
        "assumed_office_date": null,
        "cross_reference_symbols": [],
        "gender": "male",
        "ethnicity": "Han",
        "rank": null,
        "rank_chinese": null,
        "other_notes": []
      },
      {
        "name_pinyin": "Chen Fukuan",
        "name_chinese": "陳福寬",
        "dob_year": null,
        "dob_month": null,
        "assumed_office_date": null,
        "cross_reference_symbols": [],
        "gender": "male",
        "ethnicity": "Han",
        "rank": null,
        "rank_chinese": null,
        "other_notes": []
      },
      {
        "name_pinyin": "Lin Guoyao",
        "name_chinese": "林国耀",
        "dob_year": null,
        "dob_month": null,
        "assumed_office_date": null,
        "cross_reference_symbols": [],
        "gender": "male",
        "ethnicity": "Han",
        "rank": null,
        "rank_chinese": null,
        "other_notes": []
      },
      {
        "name_pinyin": "Hang Yuanxiang",
        "name_chinese": "杭元祥",
        "dob_year": null,
        "dob_month": null,
        "assumed_office_date": null,
        "cross_reference_symbols": [],
        "gender": "male",
        "ethnicity": "Han",
        "rank": null,
        "rank_chinese": null,
        "other_notes": []
      },
      {
        "name_pinyin": "Zheng Qingdong",
        "name_chinese": "鄭慶東",
        "dob_year": null,
        "dob_month": null,
        "assumed_office_date": null,
        "cross_reference_symbols": [],
        "gender": "male",
        "ethnicity": "Han",
        "rank": null,
        "rank_chinese": null,
        "other_notes": []
      },
      {
        "name_pinyin": "Fang Lingmin",
        "name_chinese": "房靈敏",
        "dob_year": null,
        "dob_month": null,
        "assumed_office_date": null,
        "cross_reference_symbols": [],
        "gender": "male",
        "ethnicity": "Han",
        "rank": null,
        "rank_chinese": null,
        "other_notes": []
      },
      {
        "name_pinyin": "Zhao Shiyong",
        "name_chinese": "趙世勇",
        "dob_year": null,
        "dob_month": null,
        "assumed_office_date": null,
        "cross_reference_symbols": [],
        "gender": "male",
        "ethnicity": "Han",
        "rank": null,
        "rank_chinese": null,
        "other_notes": []
      },
      {
        "name_pinyin": "Hu Yuhai",
        "name_chinese": "胡瑜海",
        "dob_year": null,
        "dob_month": null,
        "assumed_office_date": null,
        "cross_reference_symbols": [],
        "gender": "male",
        "ethnicity": "Han",
        "rank": null,
        "rank_chinese": null,
        "other_notes": []
      },
      {
        "name_pinyin": "Hou Kai",
        "name_chinese": "侯凱",
        "dob_year": null,
        "dob_month": null,
        "assumed_office_date": null,
        "cross_reference_symbols": [
          "◎"
        ],
        "gender": "male",
        "ethnicity": "Han",
        "rank": null,
        "rank_chinese": null,
        "other_notes": []
      },
      {
        "name_pinyin": "Hou Ximin",
        "name_chinese": "侯珉",
        "dob_year": null,
        "dob_month": null,
        "assumed_office_date": null,
        "cross_reference_symbols": [],
        "gender": "male",
        "ethnicity": "Han",
        "rank": null,
        "rank_chinese": null,
        "other_notes": []
      },
      {
        "name_pinyin": "Shi Kehui",
        "name_chinese": "施克輝",
        "dob_year": null,
        "dob_month": null,
        "assumed_office_date": null,
        "cross_reference_symbols": [],
        "gender": "male",
        "ethnicity": "Han",
        "rank": null,
        "rank_chinese": null,
        "other_notes": []
      },
      {
        "name_pinyin": "Jiang Xinjun",
        "name_chinese": "姜新軍",
        "dob_year": null,
        "dob_month": null,
        "assumed_office_date": null,
        "cross_reference_symbols": [],
        "gender": "male",
        "ethnicity": "Han",
        "rank": null,
        "rank_chinese": null,
        "other_notes": []
      },
      {
        "name_pinyin": "Lou Chunsi",
        "name_chinese": "婁純泗",
        "dob_year": null,
        "dob_month": null,
        "assumed_office_date": null,
        "cross_reference_symbols": [],
        "gender": "male",
        "ethnicity": "Han",
        "rank": null,
        "rank_chinese": null,
        "other_notes": []
      },
      {
        "name_pinyin": "Qin Bin",
        "name_chinese": "秦斌",
        "dob_year": null,
        "dob_month": null,
        "assumed_office_date": null,
        "cross_reference_symbols": [],
        "gender": "male",
        "ethnicity": "Han",
        "rank": null,
        "rank_chinese": null,
        "other_notes": []
      },
      {
        "name_pinyin": "Mo Yongcheng",
        "name_chinese": "莫永成",
        "dob_year": null,
        "dob_month": null,
        "assumed_office_date": null,
        "cross_reference_symbols": [],
        "gender": "male",
        "ethnicity": "Han",
        "rank": null,
        "rank_chinese": null,
        "other_notes": []
      },
      {
        "name_pinyin": "Xia Hongmin",
        "name_chinese": "夏紅民",
        "dob_year": null,
        "dob_month": null,
        "assumed_office_date": null,
        "cross_reference_symbols": [],
        "gender": "male",
        "ethnicity": "Han",
        "rank": null,
        "rank_chinese": null,
        "other_notes": []
      },
      {
        "name_pinyin": "Gao Fei (Miao)",
        "name_chinese": "高飛",
        "dob_year": null,
        "dob_month": null,
        "assumed_office_date": null,
        "cross_reference_symbols": [],
        "gender": "male",
        "ethnicity": "Miao",
        "rank": null,
        "rank_chinese": null,
        "other_notes": []
      },
      {
        "name_pinyin": "Gao Bo",
        "name_chinese": "高波",
        "dob_year": null,
        "dob_month": null,
        "assumed_office_date": null,
        "cross_reference_symbols": [],
        "gender": "male",
        "ethnicity": "Han",
        "rank": null,
        "rank_chinese": null,
        "other_notes": []
      },
      {
        "name_pinyin": "Guo Wenqi",
        "name_chinese": "郭文奇",
        "dob_year": null,
        "dob_month": null,
        "assumed_office_date": null,
        "cross_reference_symbols": [],
        "gender": "male",
        "ethnicity": "Han",
        "rank": null,
        "rank_chinese": null,
        "other_notes": []
      },
      {
        "name_pinyin": "Yin Bai (Naxi)",
        "name_chinese": "誾柏",
        "dob_year": null,
        "dob_month": null,
        "assumed_office_date": null,
        "cross_reference_symbols": [],
        "gender": "male",
        "ethnicity": "Naxi",
        "rank": null,
        "rank_chinese": null,
        "other_notes": []
      },
      {
        "name_pinyin": "Tu Gengxin",
        "name_chinese": "涂更新",
        "dob_year": null,
        "dob_month": null,
        "assumed_office_date": null,
        "cross_reference_symbols": [],
        "gender": "male",
        "ethnicity": "Han",
        "rank": null,
        "rank_chinese": null,
        "other_notes": []
      },
      {
        "name_pinyin": "Huang Liangbo",
        "name_chinese": "黄良波",
        "dob_year": null,
        "dob_month": null,
        "assumed_office_date": null,
        "cross_reference_symbols": [],
        "gender": "male",
        "ethnicity": "Han",
        "rank": null,
        "rank_chinese": null,
        "other_notes": []
      },
      {
        "name_pinyin": "Gong Tanghua",
        "name_chinese": "龔堂華",
        "dob_year": null,
        "dob_month": null,
        "assumed_office_date": null,
        "cross_reference_symbols": [],
        "gender": "male",
        "ethnicity": "Han",
        "rank": null,
        "rank_chinese": null,
        "other_notes": []
      },
      {
        "name_pinyin": "Cui Peng",
        "name_chinese": "崔鵬",
        "dob_year": null,
        "dob_month": null,
        "assumed_office_date": null,
        "cross_reference_symbols": [],
        "gender": "male",
        "ethnicity": "Han",
        "rank": null,
        "rank_chinese": null,
        "other_notes": []
      },
      {
        "name_pinyin": "Han Xianfeng",
        "name_chinese": "韓憲鋒",
        "dob_year": null,
        "dob_month": null,
        "assumed_office_date": null,
        "cross_reference_symbols": [],
        "gender": "male",
        "ethnicity": "Han",
        "rank": null,
        "rank_chinese": null,
        "other_notes": []
      },
      {
        "name_pinyin": "Yu Hongqiu (f)",
        "name_chinese": "喻紅秋",
        "dob_year": null,
        "dob_month": null,
        "assumed_office_date": null,
        "cross_reference_symbols": [],
        "gender": "female",
        "ethnicity": "Han",
        "rank": null,
        "rank_chinese": null,
        "other_notes": []
      },
      {
        "name_pinyin": "Cheng Dongfang",
        "name_chinese": "程東方",
        "dob_year": null,
        "dob_month": null,
        "assumed_office_date": null,
        "cross_reference_symbols": [],
        "gender": "male",
        "ethnicity": "Han",
        "rank": null,
        "rank_chinese": null,
        "other_notes": []
      },
      {
        "name_pinyin": "Cheng Lifeng",
        "name_chinese": "程立峰",
        "dob_year": null,
        "dob_month": null,
        "assumed_office_date": null,
        "cross_reference_symbols": [],
        "gender": "male",
        "ethnicity": "Han",
        "rank": null,
        "rank_chinese": null,
        "other_notes": []
      },
      {
        "name_pinyin": "Fu Kui",
        "name_chinese": "傅奎",
        "dob_year": null,
        "dob_month": null,
        "assumed_office_date": null,
        "cross_reference_symbols": [],
        "gender": "male",
        "ethnicity": "Han",
        "rank": null,
        "rank_chinese": null,
        "other_notes": []
      },
      {
        "name_pinyin": "Fu Mingxian",
        "name_chinese": "傅明先",
        "dob_year": null,
        "dob_month": null,
        "assumed_office_date": null,
        "cross_reference_symbols": [],
        "gender": "male",
        "ethnicity": "Han",
        "rank": null,
        "rank_chinese": null,
        "other_notes": []
      },
      {
        "name_pinyin": "La Yifan",
        "name_chinese": "臘翊凡",
        "dob_year": null,
        "dob_month": null,
        "assumed_office_date": null,
        "cross_reference_symbols": [],
        "gender": "male",
        "ethnicity": "Han",
        "rank": null,
        "rank_chinese": null,
        "other_notes": []
      },
      {
        "name_pinyin": "Pu Yufei",
        "name_chinese": "蒲宇飛",
        "dob_year": null,
        "dob_month": null,
        "assumed_office_date": null,
        "cross_reference_symbols": [],
        "gender": "male",
        "ethnicity": "Han",
        "rank": null,
        "rank_chinese": null,
        "other_notes": []
      },
      {
        "name_pinyin": "Liao Xiyuan",
        "name_chinese": "廖西元",
        "dob_year": null,
        "dob_month": null,
        "assumed_office_date": null,
        "cross_reference_symbols": [],
        "gender": "male",
        "ethnicity": "Han",
        "rank": null,
        "rank_chinese": null,
        "other_notes": []
      },
      {
        "name_pinyin": "Liao Jianyu",
        "name_chinese": "廖建宇",
        "dob_year": null,
        "dob_month": null,
        "assumed_office_date": null,
        "cross_reference_symbols": [],
        "gender": "male",
        "ethnicity": "Han",
        "rank": null,
        "rank_chinese": null,
        "other_notes": []
      },
      {
        "name_pinyin": "Miao Wenjiang",
        "name_chinese": "繆文江",
        "dob_year": null,
        "dob_month": null,
        "assumed_office_date": null,
        "cross_reference_symbols": [],
        "gender": "male",
        "ethnicity": "Han",
        "rank": null,
        "rank_chinese": null,
        "other_notes": []
      },
      {
        "name_pinyin": "Fan Dazhi",
        "name_chinese": "樊大志",
        "dob_year": null,
        "dob_month": null,
        "assumed_office_date": null,
        "cross_reference_symbols": [],
        "gender": "male",
        "ethnicity": "Han",
        "rank": null,
        "rank_chinese": null,
        "other_notes": []
      },
      {
        "name_pinyin": "Teng Jiacai",
        "name_chinese": "滕佳材",
        "dob_year": null,
        "dob_month": null,
        "assumed_office_date": null,
        "cross_reference_symbols": [],
        "gender": "male",
        "ethnicity": "Han",
        "rank": null,
        "rank_chinese": null,
        "other_notes": []
      },
      {
        "name_pinyin": "Mu Hongyu (f)",
        "name_chinese": "穆紅玉",
        "dob_year": null,
        "dob_month": null,
        "assumed_office_date": null,
        "cross_reference_symbols": [],
        "gender": "female",
        "ethnicity": "Han",
        "rank": null,
        "rank_chinese": null,
        "other_notes": []
      },
      {
        "name_pinyin": "Wei Shanzhong",
        "name_chinese": "魏山忠",
        "dob_year": null,
        "dob_month": null,
        "assumed_office_date": null,
        "cross_reference_symbols": [],
        "gender": "male",
        "ethnicity": "Han",
        "rank": null,
        "rank_chinese": null,
        "other_notes": []
      }
    ]
  }
]